turbostar/__init__.py
turbostar/errors.py
turbostar-0.0.0.dev0.dist-info/LICENSE
turbostar-0.0.0.dev0.dist-info/METADATA
turbostar-0.0.0.dev0.dist-info/WHEEL
turbostar-0.0.0.dev0.dist-info/top_level.txt
turbostar-0.0.0.dev0.dist-info/RECORD
