Metadata-Version: 2.1
Name: turbostar
Version: 0.0.0.dev0
Summary: A lightweight, async scheduling system.
Home-page: https://github.com/parafoxia/Turbostar
Author: Ethan Henderson
Author-email: ethan.henderson.1998@gmail.com
License: BSD-3-Clause
Project-URL: Documentation, https://turbostar.readthedocs.io/en/latest/
Project-URL: Source, https://github.com/parafoxia/Turbostar
Project-URL: Bug Tracker, https://github.com/parafoxia/Turbostar/issues
Platform: UNKNOWN
Classifier: Development Status :: 1 - Planning
Classifier: Environment :: Console
Classifier: Intended Audience :: Developers
Classifier: License :: OSI Approved :: BSD License
Classifier: Natural Language :: English
Classifier: Operating System :: MacOS
Classifier: Operating System :: Microsoft :: Windows
Classifier: Operating System :: OS Independent
Classifier: Operating System :: POSIX
Classifier: Operating System :: Unix
Classifier: Programming Language :: Python :: 3
Classifier: Programming Language :: Python :: 3 :: Only
Classifier: Programming Language :: Python :: 3.7
Classifier: Programming Language :: Python :: 3.8
Classifier: Programming Language :: Python :: 3.9
Classifier: Programming Language :: Python :: 3.10
Classifier: Programming Language :: Python :: Implementation :: CPython
Classifier: Topic :: Office/Business :: Scheduling
Classifier: Topic :: Software Development
Classifier: Topic :: Utilities
Classifier: Typing :: Typed
Requires-Python: >=3.7.0
License-File: LICENSE
